pyndamics3/__init__.py
pyndamics3/_modidx.py
pyndamics3/_nbdev.py
pyndamics3/chem.py
pyndamics3/core.py
pyndamics3/fit.py
pyndamics3/mcmc.py
pyndamics3/testit.py
pyndamics3-0.0.36.dist-info/LICENSE
pyndamics3-0.0.36.dist-info/METADATA
pyndamics3-0.0.36.dist-info/WHEEL
pyndamics3-0.0.36.dist-info/entry_points.txt
pyndamics3-0.0.36.dist-info/top_level.txt
pyndamics3-0.0.36.dist-info/RECORD
