Metadata-Version: 2.1
Name: pyndamics3
Version: 0.0.36
Summary: Python Numerical Dynamics Simulator
Home-page: https://github.com/bblais/pyndamics3/tree/master/
Author: Brian Blais
Author-email: bblais@bryant.edu
License: Apache Software License 2.0
Keywords: python,dynamics,ode,systems
Classifier: Development Status :: 3 - Alpha
Classifier: Intended Audience :: Developers
Classifier: Natural Language :: English
Classifier: Programming Language :: Python :: 3.6
Classifier: Programming Language :: Python :: 3.7
Classifier: Programming Language :: Python :: 3.8
Classifier: Programming Language :: Python :: 3.9
Classifier: Programming Language :: Python :: 3.10
Classifier: License :: OSI Approved :: Apache Software License
Requires-Python: >=3.6
License-File: LICENSE
Requires-Dist: matplotlib
Requires-Dist: scipy
Requires-Dist: emcee
Requires-Dist: lmfit
Requires-Dist: numdifftools
Requires-Dist: numba
Requires-Dist: tqdm
Provides-Extra: dev
